MANIFEST.in
README.rst
setup.py
pyoutube/__init__.py
pyoutube/uploader.py
pyoutube.egg-info/PKG-INFO
pyoutube.egg-info/SOURCES.txt
pyoutube.egg-info/dependency_links.txt
pyoutube.egg-info/not-zip-safe
pyoutube.egg-info/requires.txt
pyoutube.egg-info/top_level.txt