Metadata-Version: 1.1
Name: pyoutube
Version: 0.5
Summary: Upload videos to youtube using OAuth2.0 and the youtube API
Home-page: https://github.com/lpbrown999/pyoutube
Author: lpbrown999
Author-email: lpbrown999@gmail.com
License: MIT
Keywords: youtube upload uploader
Platform: UNKNOWN
Classifier: Development Status :: 4 - Beta
Classifier: License :: OSI Approved :: MIT License
Classifier: Programming Language :: Python :: 3
Classifier: Topic :: Internet :: WWW/HTTP
Classifier: Topic :: Multimedia :: Video
